[
    { "id": 1, "part": "Principes et valeurs de la République", "category": "CR", "question": "Parmi les propositions suivantes, laquelle constitue une participation citoyenne ?" },
    { "id": 2, "part": "Principes et valeurs de la République", "category": "CR", "question": "Que garantit la liberté d’expression ?" },
    { "id": 3, "part": "Principes et valeurs de la République", "category": "CR", "question": "À quoi sert un titre de séjour ?" },
    { "id": 4, "part": "Principes et valeurs de la République", "category": "CR", "question": "La liberté de circulation permet à toute personne de :" },
    { "id": 5, "part": "Principes et valeurs de la République", "category": "CR", "question": "Sur quel site internet peut-on retrouver le symbole de la République française ?" },
    { "id": 6, "part": "Principes et valeurs de la République", "category": "CR", "question": "Complétez ces paroles de la Marseillaise : \"Aux armes […] ! Formez vos bataillons\"" },
    { "id": 7, "part": "Principes et valeurs de la République", "category": "CR", "question": "Complétez les paroles de la Marseillaise : \"Allons enfants de la patrie […]\"" },
    { "id": 8, "part": "Principes et valeurs de la République", "category": "CR", "question": "En application de la liberté individuelle, quelle proposition est correcte ? Une personne peut :" },
    { "id": 9, "part": "Principes et valeurs de la République", "category": "CR", "question": "Concernant la pratique de la religion, quelle proposition est correcte ?" },
    { "id": 10, "part": "Principes et valeurs de la République", "category": "CR", "question": "En tant que parent, peut-on refuser que son enfant participe aux cours de sport à l'école car ils sont mixtes ?" },
    { "id": 11, "part": "Principes et valeurs de la République", "category": "CR", "question": "Quelle est la devise de la France ?" },
    { "id": 12, "part": "Principes et valeurs de la République", "category": "CR", "question": "La répudiation de sa femme est :" },
    { "id": 13, "part": "Principes et valeurs de la République", "category": "CR", "question": "Les impôts permettent de financer les dépenses publiques. Quelle proposition est correcte ?" },
    { "id": 14, "part": "Principes et valeurs de la République", "category": "CR", "question": "Peut-on brûler publiquement un drapeau français ?" },
    { "id": 15, "part": "Principes et valeurs de la République", "category": "CR", "question": "Que fait l’État pour lutter contre les discriminations ?" },
    { "id": 16, "part": "Principes et valeurs de la République", "category": "CR", "question": "Que représente Marianne ?" },
    { "id": 17, "part": "Principes et valeurs de la République", "category": "CR", "question": "Qu'est-ce que la liberté d'association ?" },
    { "id": 18, "part": "Principes et valeurs de la République", "category": "CR", "question": "Qu'est-ce que la liberté ?" },
    { "id": 19, "part": "Principes et valeurs de la République", "category": "CR", "question": "Qu'est-ce que la Marseillaise ?" },
    { "id": 20, "part": "Principes et valeurs de la République", "category": "CR", "question": "Sur quel document peut-on voir Marianne ?" },
    { "id": 21, "part": "Principes et valeurs de la République", "category": "CR", "question": "Un employeur refuse d’embaucher des femmes dans son entreprise. Que dit la loi ?" },
    { "id": 22, "part": "Principes et valeurs de la République", "category": "CR", "question": "Une des valeurs de la devise républicaine est l'égalité. Qu'est-ce que cela signifie ?" },
    { "id": 23, "part": "Principes et valeurs de la République", "category": "CR", "question": "Quelle est la place de la langue française dans la République ?" },
    { "id": 24, "part": "Principes et valeurs de la République", "category": "CR", "question": "Quels sont des symboles officiels de la République française ?" },
    { "id": 25, "part": "Principes et valeurs de la République", "category": "CR", "question": "A-t-on le droit d'insulter publiquement quelqu’un parce qu’il est différent (handicap, apparence physique, sexe…) ?" },
    { "id": 26, "part": "Principes et valeurs de la République", "category": "CR", "question": "Le régime de la France est :" },
    { "id": 27, "part": "Principes et valeurs de la République", "category": "CR", "question": "Pourquoi le principe de laïcité doit-il être respecté à l'école ?" },
    { "id": 28, "part": "Principes et valeurs de la République", "category": "CR", "question": "En quelle année la loi de séparation des Églises et de l'Etat a-t-elle été votée ?" },
    { "id": 29, "part": "Principes et valeurs de la République", "category": "CR", "question": "Une personne a-t-elle le droit de ne pas croire en une religion ?" },
    { "id": 30, "part": "Principes et valeurs de la République", "category": "CR", "question": "Quel droit est garanti par la laïcité ?" },
    { "id": 31, "part": "Principes et valeurs de la République", "category": "CR", "question": "À l'école publique, qui peut porter des signes religieux très visibles ?" },
    { "id": 32, "part": "Principes et valeurs de la République", "category": "CR", "question": "Selon le principe de laïcité, que signifie la neutralité de l’État ?" },
    { "id": 33, "part": "Principes et valeurs de la République", "category": "CR", "question": "Que peut faire un usager du service public dans une mairie ?" },
    { "id": 34, "part": "Principes et valeurs de la République", "category": "CR", "question": "Qui doit respecter le principe de neutralité religieuse dans une préfecture ?" },
    { "id": 35, "part": "Principes et valeurs de la République", "category": "CR", "question": "La laïcité impose-t-elle aux agents publics d'être neutres vis-à-vis des usagers ?" },
    { "id": 36, "part": "Principes et valeurs de la République", "category": "CR", "question": "Que garantit le principe de laïcité ?" },
    { "id": 37, "part": "Principes et valeurs de la République", "category": "CR", "question": "A-t-on le droit de changer de religion ?" },
    { "id": 38, "part": "Principes et valeurs de la République", "category": "CR", "question": "Que représente la laïcité ?" },
    { "id": 39, "part": "Principes et valeurs de la République", "category": "CR", "question": "Qu'est ce qui est interdit par la Charte de la laïcité à l'école ?" },
    { "id": 40, "part": "Principes et valeurs de la République", "category": "CR", "question": "Que dit l'article 1er de la Constitution française ?" },
  
    { "id": 41, "part": "Système institutionnel et politique", "category": "CR", "question": "Qu'est-ce que l'État de droit ?" },
    { "id": 42, "part": "Système institutionnel et politique", "category": "CR", "question": "Le président de la République a commis un crime. Quelle proposition est correcte ?" },
    { "id": 43, "part": "Système institutionnel et politique", "category": "CR", "question": "La loi est l'expression de :" },
    { "id": 44, "part": "Système institutionnel et politique", "category": "CR", "question": "Quelle est la durée du mandat du conseil municipal et du maire ?" },
    { "id": 45, "part": "Système institutionnel et politique", "category": "CR", "question": "Que garantit l’État de droit ?" },
    { "id": 46, "part": "Système institutionnel et politique", "category": "CR", "question": "Une personne peut-elle voter à la place d'une autre ?" },
    { "id": 47, "part": "Système institutionnel et politique", "category": "CR", "question": "Est-ce que le vote est obligatoire ?" },
    { "id": 48, "part": "Système institutionnel et politique", "category": "CR", "question": "À la fin de son mandat, le président de la République peut-il décider de rester au pouvoir ?" },
    { "id": 49, "part": "Système institutionnel et politique", "category": "CR", "question": "Qui dirige l'action du Gouvernement ?" },
    { "id": 50, "part": "Système institutionnel et politique", "category": "CR", "question": "Qui nomme le Premier ministre ?" },
    { "id": 51, "part": "Système institutionnel et politique", "category": "CR", "question": "Quelle est l'organisation administrative de la France ?" },
    { "id": 52, "part": "Système institutionnel et politique", "category": "CR", "question": "Qu'est-ce que le pouvoir législatif ? Le pouvoir :" },
    { "id": 53, "part": "Système institutionnel et politique", "category": "CR", "question": "Pourquoi séparer les trois pouvoirs dans une démocratie ?" },
    { "id": 54, "part": "Système institutionnel et politique", "category": "CR", "question": "Qui sanctionne l'auteur d'un vol ?" },
    { "id": 55, "part": "Système institutionnel et politique", "category": "CR", "question": "Quel est le rôle du gouvernement ?" },
    { "id": 56, "part": "Système institutionnel et politique", "category": "CR", "question": "Que se passe-t-il si un ministre ne respecte pas la loi ?" },
    { "id": 57, "part": "Système institutionnel et politique", "category": "CR", "question": "Combien de députés composent l’Assemblée nationale ?" },
    { "id": 58, "part": "Système institutionnel et politique", "category": "CR", "question": "Qui peut voter aux élections en France ?" },
    { "id": 59, "part": "Système institutionnel et politique", "category": "CR", "question": "Pour combien de temps sont élus les sénateurs ?" },
    { "id": 60, "part": "Système institutionnel et politique", "category": "CR", "question": "La séparation des pouvoirs est un principe fondamental. Quels sont les trois pouvoirs concernés ?" },
    { "id": 61, "part": "Système institutionnel et politique", "category": "CR", "question": "Est-ce que le président de la République a tous les pouvoirs ?" },
    { "id": 62, "part": "Système institutionnel et politique", "category": "CR", "question": "Qui est le préfet ?" },
    { "id": 63, "part": "Système institutionnel et politique", "category": "CR", "question": "Quelle condition est nécessaire pour voter aux élections ?" },
    { "id": 64, "part": "Système institutionnel et politique", "category": "CR", "question": "Qui dirige la commune ?" },
    { "id": 65, "part": "Système institutionnel et politique", "category": "CR", "question": "Quel est le régime politique de la France aujourd'hui ?" },
    { "id": 66, "part": "Système institutionnel et politique", "category": "CR", "question": "Qu'est-ce que l'Hôtel de Matignon ?" },
    { "id": 67, "part": "Système institutionnel et politique", "category": "CR", "question": "Le Parlement est composé :" },
    { "id": 68, "part": "Système institutionnel et politique", "category": "CR", "question": "Quel est le rôle du président de la République ?" },
    { "id": 69, "part": "Système institutionnel et politique", "category": "CR", "question": "Quel est le rôle du Premier ministre ?" },
    { "id": 70, "part": "Système institutionnel et politique", "category": "CR", "question": "Qui est le chef du Gouvernement ?" },
    { "id": 71, "part": "Système institutionnel et politique", "category": "CR", "question": "Combien y a-t-il de régions en France ?" },
    { "id": 72, "part": "Système institutionnel et politique", "category": "CR", "question": "Quel est le rôle du Défenseur des droits ?" },
    { "id": 73, "part": "Système institutionnel et politique", "category": "CR", "question": "Depuis quand l'euro est-elle la monnaie unique ?" },
    { "id": 74, "part": "Système institutionnel et politique", "category": "CR", "question": "Quel est le rôle principal du département ?" },
    { "id": 75, "part": "Système institutionnel et politique", "category": "CR", "question": "Quel est le rôle principal des communes ?" },
    { "id": 76, "part": "Système institutionnel et politique", "category": "CR", "question": "Combien de communes environ existe-t-il en France ?" },
    { "id": 77, "part": "Système institutionnel et politique", "category": "CR", "question": "Quel traité concerne la construction de l'Union européenne ?" },
    { "id": 78, "part": "Système institutionnel et politique", "category": "CR", "question": "Quel État a quitté l'Union européenne en 2020 ?" },
    { "id": 79, "part": "Système institutionnel et politique", "category": "CR", "question": "Quelle est la devise de l’Union européenne ?" },
    { "id": 80, "part": "Système institutionnel et politique", "category": "CR", "question": "Quel est l'hymne de l'Union européenne ?" },
    { "id": 81, "part": "Système institutionnel et politique", "category": "CR", "question": "De quoi est composé le drapeau européen ?" },
    { "id": 82, "part": "Système institutionnel et politique", "category": "CR", "question": "De quelle couleur est le drapeau européen ?" },
    { "id": 83, "part": "Système institutionnel et politique", "category": "CR", "question": "En quelle année le traité de Maastricht, qui marque la fondation de l'Union européenne, a-t-il été signé ?" },
    { "id": 84, "part": "Système institutionnel et politique", "category": "CR", "question": "Où est le siège du Parlement européen ?" },
    { "id": 85, "part": "Système institutionnel et politique", "category": "CR", "question": "Où est le siège de la Commission européenne ?" },
    { "id": 86, "part": "Système institutionnel et politique", "category": "CR", "question": "Quel État n'est pas membre de l'Union européenne ?" },
    { "id": 87, "part": "Système institutionnel et politique", "category": "CR", "question": "Quand célèbre-t-on la journée de l'Europe ?" },
    { "id": 88, "part": "Système institutionnel et politique", "category": "CR", "question": "À quelle fréquence les élections européennes sont-elles organisées ?" },
    { "id": 89, "part": "Système institutionnel et politique", "category": "CR", "question": "Quelle condition est nécessaire pour voter aux élections européennes ?" },
    { "id": 90, "part": "Système institutionnel et politique", "category": "CR", "question": "Quel pays est un pays fondateur de l'Union européenne ?" },
  
    { "id": 91, "part": "Droits et devoirs", "category": "CR", "question": "À quelle liberté la PMA fait-elle référence ?" },
    { "id": 92, "part": "Droits et devoirs", "category": "CR", "question": "Au nom de quoi l'État justifie-t-il la restriction des droits ?" },
    { "id": 93, "part": "Droits et devoirs", "category": "CR", "question": "Concernant le droit de se marier, quelle proposition est correcte ?" },
    { "id": 94, "part": "Droits et devoirs", "category": "CR", "question": "Est-il toujours possible de divorcer ?" },
    { "id": 95, "part": "Droits et devoirs", "category": "CR", "question": "La peine de mort est :" },
    { "id": 96, "part": "Droits et devoirs", "category": "CR", "question": "Laquelle de ces citations est inscrite dans la Déclaration des Droits de l'homme et du Citoyen de 1789 ?" },
    { "id": 97, "part": "Droits et devoirs", "category": "CR", "question": "Le recours à l'avortement est-il autorisé ?" },
    { "id": 98, "part": "Droits et devoirs", "category": "CR", "question": "Que contient la Constitution ?" },
    { "id": 99, "part": "Droits et devoirs", "category": "CR", "question": "Que garantit la liberté de la presse ?" },
    { "id": 100, "part": "Droits et devoirs", "category": "CR", "question": "Que prévoit la Charte de l'environnement ?" },
    { "id": 101, "part": "Droits et devoirs", "category": "CR", "question": "Que signifie la dignité humaine ?" },
    { "id": 102, "part": "Droits et devoirs", "category": "CR", "question": "Que signifie le droit de manifester ?" },
    { "id": 103, "part": "Droits et devoirs", "category": "CR", "question": "Que signifie PMA ?" },
    { "id": 104, "part": "Droits et devoirs", "category": "CR", "question": "Quel texte est le plus difficile à modifier ?" },
    { "id": 105, "part": "Droits et devoirs", "category": "CR", "question": "Quelle liberté permet à une personne de croire en la religion de son choix ?" },
    { "id": 106, "part": "Droits et devoirs", "category": "CR", "question": "Qu'est-ce que le droit de grève ?" },
    { "id": 107, "part": "Droits et devoirs", "category": "CR", "question": "Qu'est-ce que la Constitution ?" },
    { "id": 108, "part": "Droits et devoirs", "category": "CR", "question": "Qui peut demander à avorter ?" },
    { "id": 109, "part": "Droits et devoirs", "category": "CR", "question": "Une femme majeure de nationalité française a-t-elle le droit de voter aux élections ?" },
    { "id": 110, "part": "Droits et devoirs", "category": "CR", "question": "Concernant l'utilisation des réseaux sociaux, quelle proposition est correcte ?" },
    { "id": 111, "part": "Droits et devoirs", "category": "CR", "question": "Jeter un mégot par terre est :" },
    { "id": 112, "part": "Droits et devoirs", "category": "CR", "question": "L'État peut-il limiter les droits et libertés ?" },
    { "id": 113, "part": "Droits et devoirs", "category": "CR", "question": "Parmi ces actions, laquelle permet d'adopter une attitude respectueuse de l’environnement ?" },
    { "id": 114, "part": "Droits et devoirs", "category": "CR", "question": "Quelle proposition constitue une obligation ?" },
    { "id": 115, "part": "Droits et devoirs", "category": "CR", "question": "Pour quel motif peut-on limiter la liberté d'expression ?" },
    { "id": 116, "part": "Droits et devoirs", "category": "CR", "question": "Pourquoi doit-on trier ses déchets ?" },
    { "id": 117, "part": "Droits et devoirs", "category": "CR", "question": "Que doit faire une victime de violences ?" },
    { "id": 118, "part": "Droits et devoirs", "category": "CR", "question": "Que doit-on faire face aux ordres des policiers ou gendarmes ?" },
    { "id": 119, "part": "Droits et devoirs", "category": "CR", "question": "Quel est le rôle de la police ?" },
    { "id": 120, "part": "Droits et devoirs", "category": "CR", "question": "Quel est un exemple d’assistance à personne en danger ?" },
    { "id": 121, "part": "Droits et devoirs", "category": "CR", "question": "Quel exemple illustre une limitation de liberté pour protéger l'intérêt général ?" },
    { "id": 122, "part": "Droits et devoirs", "category": "CR", "question": "Quelle est l’attitude à avoir lorsque qu'on est témoin de violences ?" },
    { "id": 123, "part": "Droits et devoirs", "category": "CR", "question": "Quelle est l'infraction la plus grave ?" },
    { "id": 124, "part": "Droits et devoirs", "category": "CR", "question": "Quelle obligation concerne toutes les personnes résidant en France quelle que soit leur nationalité ?" },
    { "id": 125, "part": "Droits et devoirs", "category": "CR", "question": "Quelle proposition représente un exemple de crime ?" },
    { "id": 126, "part": "Droits et devoirs", "category": "CR", "question": "Quelle proposition représente un exemple de délit ?" },
    { "id": 127, "part": "Droits et devoirs", "category": "CR", "question": "Qui veille au maintien de l’ordre public ?" },
    { "id": 128, "part": "Droits et devoirs", "category": "CR", "question": "S'agissant des déchets, quelle proposition est correcte ?" },
  
    { "id": 129, "part": "Histoire géographie et culture", "category": "CR", "question": "Quel était le surnom de Louis XIV ?" },
    { "id": 130, "part": "Histoire géographie et culture", "category": "CR", "question": "Quel roi de France a été exécuté pendant la Révolution française ?" },
    { "id": 131, "part": "Histoire géographie et culture", "category": "CR", "question": "En quelle année Napoléon Ier est-il devenu empereur ?" },
    { "id": 132, "part": "Histoire géographie et culture", "category": "CR", "question": "Lequel de ces personnages a un lien avec la République française ?" },
    { "id": 133, "part": "Histoire géographie et culture", "category": "CR", "question": "De quand date l'appel à la résistance du général de Gaulle ?" },
    { "id": 134, "part": "Histoire géographie et culture", "category": "CR", "question": "Pourquoi la Shoah est-elle étudiée à l'école ?" },
    { "id": 135, "part": "Histoire géographie et culture", "category": "CR", "question": "Quel pays a été colonisé par la France ?" },
    { "id": 136, "part": "Histoire géographie et culture", "category": "CR", "question": "Depuis quand les Français élisent-ils le président de la République au suffrage universel direct ?" },
    { "id": 137, "part": "Histoire géographie et culture", "category": "CR", "question": "Quelle est la première étape de la construction européenne en 1951 ?" },
    { "id": 138, "part": "Histoire géographie et culture", "category": "CR", "question": "Durant le mandat de quel président la peine de mort a-t-elle été abolie ?" },
    { "id": 139, "part": "Histoire géographie et culture", "category": "CR", "question": "Quel régime politique a été mis en place pendant la Révolution française en 1792 ?" },
    { "id": 140, "part": "Histoire géographie et culture", "category": "CR", "question": "Qui était une figure de la Résistance française pendant la Seconde Guerre mondiale ?" },
    { "id": 141, "part": "Histoire géographie et culture", "category": "CR", "question": "En 1944, qu'est-ce qui a changé pour les femmes ?" },
    { "id": 142, "part": "Histoire géographie et culture", "category": "CR", "question": "Quelle organisation internationale a été créée en 1945 après la Seconde Guerre mondiale ?" },
    { "id": 143, "part": "Histoire géographie et culture", "category": "CR", "question": "Quelle peine a été supprimée en 1981 ?" },
    { "id": 144, "part": "Histoire géographie et culture", "category": "CR", "question": "En quelle année l'euro est-elle devenue la monnaie utilisée en France ?" },
    { "id": 145, "part": "Histoire géographie et culture", "category": "CR", "question": "En quelle année a commencé la Première Guerre mondiale ?" },
    { "id": 146, "part": "Histoire géographie et culture", "category": "CR", "question": "Où a eu lieu le débarquement en 1944 ?" },
    { "id": 147, "part": "Histoire géographie et culture", "category": "CR", "question": "Quel continent a été le plus concerné par la décolonisation française après la Seconde Guerre mondiale ?" },
    { "id": 148, "part": "Histoire géographie et culture", "category": "CR", "question": "Que fête-t-on le 8 mai ?" },
    { "id": 149, "part": "Histoire géographie et culture", "category": "CR", "question": "Quelle mer ou océan borde la France métropolitaine ?" },
    { "id": 150, "part": "Histoire géographie et culture", "category": "CR", "question": "Quel pays a une frontière terrestre avec la France métropolitaine ?" },
    { "id": 151, "part": "Histoire géographie et culture", "category": "CR", "question": "Quelle ville française est un port maritime ?" },
    { "id": 152, "part": "Histoire géographie et culture", "category": "CR", "question": "Quelle mer se situe entre la France et l'Angleterre ?" },
    { "id": 153, "part": "Histoire géographie et culture", "category": "CR", "question": "Qu'est ce que la France d'outre-mer ?" },
    { "id": 154, "part": "Histoire géographie et culture", "category": "CR", "question": "Quelle chaîne de montagnes est située entre la France et l’Espagne ?" },
    { "id": 155, "part": "Histoire géographie et culture", "category": "CR", "question": "Quelle île française se trouve dans l'océan Indien ?" },
    { "id": 156, "part": "Histoire géographie et culture", "category": "CR", "question": "Quelle est la population approximative de la France en 2025 ?" },
    { "id": 157, "part": "Histoire géographie et culture", "category": "CR", "question": "Quel fleuve traverse Paris ?" },
    { "id": 158, "part": "Histoire géographie et culture", "category": "CR", "question": "Lequel de ces pays partage des frontières terrestres avec la France ?" },
    { "id": 159, "part": "Histoire géographie et culture", "category": "CR", "question": "Quel pays a une frontière avec la France métropolitaine au nord-est ?" },
    { "id": 160, "part": "Histoire géographie et culture", "category": "CR", "question": "Où se trouvent les principales activités économiques en France ?" },
    { "id": 161, "part": "Histoire géographie et culture", "category": "CR", "question": "Parmi ces pays, lequel attire le plus de visiteurs chaque année ?" },
    { "id": 162, "part": "Histoire géographie et culture", "category": "CR", "question": "Où habite la majorité des Français ?" },
    { "id": 163, "part": "Histoire géographie et culture", "category": "CR", "question": "Quelle région est la plus peuplée ?" },
    { "id": 164, "part": "Histoire géographie et culture", "category": "CR", "question": "Quelle ville française fait partie des 10 plus grandes métropoles du pays ?" },
    { "id": 165, "part": "Histoire géographie et culture", "category": "CR", "question": "Lequel de ces départements de France est le plus touristique ?" },
    { "id": 166, "part": "Histoire géographie et culture", "category": "CR", "question": "Quand peut-on visiter gratuitement des lieux culturels en France ?" },
    { "id": 167, "part": "Histoire géographie et culture", "category": "CR", "question": "Combien de personnes parlent français dans le monde ?" },
    { "id": 168, "part": "Histoire géographie et culture", "category": "CR", "question": "Qui était Marguerite Yourcenar ?" },
    { "id": 169, "part": "Histoire géographie et culture", "category": "CR", "question": "Quel peintre est français ?" },
    { "id": 170, "part": "Histoire géographie et culture", "category": "CR", "question": "Quel musée est situé à Paris ?" },
    { "id": 171, "part": "Histoire géographie et culture", "category": "CR", "question": "Qui était Auguste Rodin ?" },
    { "id": 172, "part": "Histoire géographie et culture", "category": "CR", "question": "Quel est le classement de la langue française parmi les langues les plus parlées dans le monde ?" },
    { "id": 173, "part": "Histoire géographie et culture", "category": "CR", "question": "Quelle cathédrale célèbre a été en partie détruite par un incendie en 2019 ?" },
    { "id": 174, "part": "Histoire géographie et culture", "category": "CR", "question": "Qui était une écrivaine française célèbre ?" },
    { "id": 175, "part": "Histoire géographie et culture", "category": "CR", "question": "Qui était un célèbre musicien français ?" },
    { "id": 176, "part": "Histoire géographie et culture", "category": "CR", "question": "Qui était Auguste Renoir ?" },
    { "id": 177, "part": "Histoire géographie et culture", "category": "CR", "question": "Quelle fête est française ?" },
  
    { "id": 178, "part": "Vivre dans la société française", "category": "CR", "question": "Quel mariage est reconnu par l'État ?" },
    { "id": 179, "part": "Vivre dans la société française", "category": "CR", "question": "Auprès de quelle institution les parents peuvent-ils inscrire leur enfant à l'école publique ?" },
    { "id": 180, "part": "Vivre dans la société française", "category": "CR", "question": "En cas de divorce, qui exerce l'autorité parentale ?" },
    { "id": 181, "part": "Vivre dans la société française", "category": "CR", "question": "Quelle aide permet aux personnes qui ont des difficultés financières d'avoir un avocat ?" },
    { "id": 182, "part": "Vivre dans la société française", "category": "CR", "question": "Où faut-il déclarer la naissance d'un enfant ?" },
    { "id": 183, "part": "Vivre dans la société française", "category": "CR", "question": "Quelle est l'une des conditions pour passer l'examen du permis de conduire ?" },
    { "id": 184, "part": "Vivre dans la société française", "category": "CR", "question": "Un bail locatif est valide s'il est :" },
    { "id": 185, "part": "Vivre dans la société française", "category": "CR", "question": "Où peut-on déposer un lave-vaisselle cassé ?" },
    { "id": 186, "part": "Vivre dans la société française", "category": "CR", "question": "Quel numéro d'urgence permet d'appeler la police ?" },
    { "id": 187, "part": "Vivre dans la société française", "category": "CR", "question": "Concernant l'accès aux soins, quelle proposition est correcte ?" },
    { "id": 188, "part": "Vivre dans la société française", "category": "CR", "question": "À qui est accessible la contraception ?" },
    { "id": 189, "part": "Vivre dans la société française", "category": "CR", "question": "Qu’est-ce que le principe de confidentialité dans le domaine de la santé ?" },
    { "id": 190, "part": "Vivre dans la société française", "category": "CR", "question": "L'inscription à l'Assurance maladie est :" },
    { "id": 191, "part": "Vivre dans la société française", "category": "CR", "question": "Qui peut demander un congé parental d'éducation ?" },
    { "id": 192, "part": "Vivre dans la société française", "category": "CR", "question": "Quelles sont les affaires traitées par le conseil de prud'hommes ?" },
    { "id": 193, "part": "Vivre dans la société française", "category": "CR", "question": "Travailler sans être déclaré est :" },
    { "id": 194, "part": "Vivre dans la société française", "category": "CR", "question": "Lorsqu'un employeur veut qu'un salarié travaille plus longtemps que la durée prévue dans le contrat de travail :" },
    { "id": 195, "part": "Vivre dans la société française", "category": "CR", "question": "Quelle est la mission de France Travail ?" },
    { "id": 196, "part": "Vivre dans la société française", "category": "CR", "question": "Dans une entreprise, le droit syndical permet :" },
    { "id": 197, "part": "Vivre dans la société française", "category": "CR", "question": "Dans une entreprise, le droit de grève autorise :" },
    { "id": 198, "part": "Vivre dans la société française", "category": "CR", "question": "Quelles sont les conditions pour toucher les allocations chômage ?" },
    { "id": 199, "part": "Vivre dans la société française", "category": "CR", "question": "Qu'est-ce que l'école maternelle ?" },
    { "id": 200, "part": "Vivre dans la société française", "category": "CR", "question": "Comment s'appelle le diplôme passé par les élèves à la fin du collège ?" },
    { "id": 201, "part": "Vivre dans la société française", "category": "CR", "question": "Les parents d'élève ont le droit de :" },
    { "id": 202, "part": "Vivre dans la société française", "category": "CR", "question": "Qui peut manger à la cantine scolaire ?" },
    { "id": 203, "part": "Vivre dans la société française", "category": "CR", "question": "À quel âge commence l'instruction obligatoire des enfants ?" },
    { "id": 204, "part": "Vivre dans la société française", "category": "CR", "question": "Quel est l'âge de la majorité ?" },
    { "id": 205, "part": "Vivre dans la société française", "category": "CR", "question": "À l'école, il est interdit aux parents de :" },
    { "id": 206, "part": "Vivre dans la société française", "category": "CR", "question": "Quel motif d'absence est accepté par l'école ?" },
    { "id": 207, "part": "Vivre dans la société française", "category": "CR", "question": "Des parents ne respectent pas l'obligation d'instruction pour leurs enfants. Quelle sanction maximale risquent-ils ?" },
    { "id": 208, "part": "Vivre dans la société française", "category": "CR", "question": "Quand ont lieu les vacances scolaires de Noël ?" },
    { "id": 209, "part": "Vivre dans la société française", "category": "CR", "question": "À l'école, un enfant en situation de handicap :" }
  ]
  